README.rst
setup.py
stwitto/__init__.py
stwitto/twitt.py
stwitto.egg-info/PKG-INFO
stwitto.egg-info/SOURCES.txt
stwitto.egg-info/dependency_links.txt
stwitto.egg-info/entry_points.txt
stwitto.egg-info/requires.txt
stwitto.egg-info/top_level.txt