Metadata-Version: 1.0
Name: stwitto
Version: 0.1
Summary: Command Line Twitter Client
Home-page: https://github.com/surajnarwade/stwitto.git
Author: Suraj Narwade
Author-email: hackersvilla123@gmail.com
License: MIT
Platform: UNKNOWN
